NetHDBSCAN/__init__.py
NetHDBSCAN/percolation/__init__.py
NetHDBSCAN/percolation/_percolation.c
NetHDBSCAN/percolation/_percolation.cpython-310-darwin.so
NetHDBSCAN/percolation/_percolation.pxd
NetHDBSCAN/percolation/_percolation.pyx
NetHDBSCAN/percolation/percolation.py
NetHDBSCAN/structures/__init__.py
NetHDBSCAN/structures/_graph.c
NetHDBSCAN/structures/_graph.cpython-310-darwin.so
NetHDBSCAN/structures/_graph.pxd
NetHDBSCAN/structures/_graph.pyx
NetHDBSCAN/structures/_tree.c
NetHDBSCAN/structures/_tree.cpython-310-darwin.so
NetHDBSCAN/structures/_tree.pxd
NetHDBSCAN/structures/_tree.pyx
NetHDBSCAN/structures/_union_find.c
NetHDBSCAN/structures/_union_find.cpython-310-darwin.so
NetHDBSCAN/structures/_union_find.pxd
NetHDBSCAN/structures/_union_find.pyx
NetHDBSCAN/structures/cluster.py
NetHDBSCAN/structures/condensed_tree.py
NetHDBSCAN/structures/linkage_tree.py
NetHDBSCAN-0.0.1.dist-info/LICENSE
NetHDBSCAN-0.0.1.dist-info/METADATA
NetHDBSCAN-0.0.1.dist-info/WHEEL
NetHDBSCAN-0.0.1.dist-info/top_level.txt
NetHDBSCAN-0.0.1.dist-info/RECORD
