Metadata-Version: 2.1
Name: NetHDBSCAN
Version: 0.0.1
Summary: A graph clustering algorithm inspired by HDBSCAN
Author: Abel Verley
Author-email: Abel Verley <abel.verley@ens-paris-saclay.fr>
License: MIT
Project-URL: Homepage, https://github.com/abelmaxv/CASA-1A
Classifier: Programming Language :: Python :: 3
Classifier: Operating System :: OS Independent
Requires-Python: >=3.8
License-File: LICENSE
Provides-Extra: dev
Requires-Dist: Cython; extra == "dev"
